timezoneutils/__init__.py
timezoneutils/convert.py
timezoneutils/timezone_middleware.py
timezoneutils/tools.py
timezoneutils/utils.py
timezoneutils-0.1.0.dist-info/LICENSE
timezoneutils-0.1.0.dist-info/METADATA
timezoneutils-0.1.0.dist-info/WHEEL
timezoneutils-0.1.0.dist-info/top_level.txt
timezoneutils-0.1.0.dist-info/RECORD
